qpyr/__init__.py
qpyr/_lib/__init__.py
qpyr/_lib/data_masking.py
qpyr/_lib/draw.py
qpyr/_lib/encode.py
qpyr/_lib/error_correction.py
qpyr/_lib/matrix.py
qpyr/_lib/static.py
qpyr/_lib/utils.py
qpyr/main.py
qpyr-0.1.19.dist-info/LICENSE
qpyr-0.1.19.dist-info/METADATA
qpyr-0.1.19.dist-info/WHEEL
qpyr-0.1.19.dist-info/RECORD
