Metadata-Version: 2.1
Name: qpyr
Version: 0.1.19
Summary: Create QR Codes.
License: Apache-2.0
Keywords: qr,qrcode,qrcode-generator,qr-code
Author: Sabi
Requires-Python: >=3.9,<4.0
Classifier: License :: OSI Approved :: Apache Software License
Classifier: Programming Language :: Python :: 3
Classifier: Programming Language :: Python :: 3.9
Classifier: Programming Language :: Python :: 3.10
Classifier: Programming Language :: Python :: 3.11
Requires-Dist: Pillow (>=10.1.0,<11.0.0)
Requires-Dist: numpy (>=1.26.2,<2.0.0)
Project-URL: Source, https://github.com/sabih-h/qpyr
